py_environ.py
py_environ-0.2.dist-info/DESCRIPTION.rst
py_environ-0.2.dist-info/METADATA
py_environ-0.2.dist-info/RECORD
py_environ-0.2.dist-info/WHEEL
py_environ-0.2.dist-info/metadata.json
py_environ-0.2.dist-info/top_level.txt
