Metadata-Version: 2.0
Name: py-environ
Version: 0.2
Summary: A ConfigParser implementation with environment overrides
Home-page: UNKNOWN
Author: JM Ibanez
Author-email: hi@jmibanez.com
License: UNKNOWN
Platform: UNKNOWN
Requires-Dist: six (>=1.9.0)
